src/__init__.py
src/combine_images.py
src/download_usr_fig.py
src/image_pipeline.py
src/make_images.py
src/make_spectra.py
src/modules/__init__.py
src/modules/functions.py
src/modules/get_ancillary.py
src/modules/get_hst_cosmos.py
src/modules/panstarrs_fcns.py
sofia_image_pipeline-1.3.5.dist-info/LICENSE
sofia_image_pipeline-1.3.5.dist-info/METADATA
sofia_image_pipeline-1.3.5.dist-info/WHEEL
sofia_image_pipeline-1.3.5.dist-info/entry_points.txt
sofia_image_pipeline-1.3.5.dist-info/top_level.txt
sofia_image_pipeline-1.3.5.dist-info/RECORD
