Metadata-Version: 2.1
Name: sofia-image-pipeline
Version: 1.3.5
Summary: SIP takes a SoFiA generated source catalog and produce images for publication or quick inspection. Images include HI contours overlaid on multiwavelength images, HI moment maps, pixel-by-pixel SNR maps, pv-diagrams with SoFiA mask, and spectra with and without noise.
Home-page: https://github.com/kmhess/SoFiA-image-pipeline
Author: Kelley M. Hess
Author-email: "Kelley M. Hess" <kmhess.astro@gmail.com>
Project-URL: Homepage, https://github.com/kmhess/SoFiA-image-pipeline
Classifier: Programming Language :: Python :: 3
Classifier: License :: OSI Approved :: GNU General Public License v3 (GPLv3)
License-File: LICENSE
Requires-Dist: astropy >=5.0.2
Requires-Dist: astroquery >=0.4.7
Requires-Dist: matplotlib >=3.5.1
Requires-Dist: numpy >=1.22.0
Requires-Dist: Pillow >=10.0.1
Requires-Dist: pvextractor >=0.4
Requires-Dist: requests >=2.31.0
Requires-Dist: setuptools >=65.5.1
Requires-Dist: sphinx-rtd-theme >=1.0.0
Requires-Dist: xmltodict >=0.12.0
